flask_restful_helper/__init__.py
flask_restful_helper/flask_admin.py
flask_restful_helper/flask_admin_utils.py
flask_restful_helper/app_base/__init__.py
flask_restful_helper/app_base/clean/__init__.py
flask_restful_helper/app_base/clean/router.template
flask_restful_helper/app_base/clean/api_views/api_view.template
flask_restful_helper/app_base/clean/logics/logic.template
flask_restful_helper/app_base/clean/managers/manager.template
flask_restful_helper/app_base/clean/models/model.template
flask_restful_helper/app_base/clean/schemas/schema.template
flask_restful_helper/app_base/clean/tests/test.template
flask_restful_helper/app_base/file/__init__.py
flask_restful_helper/app_base/file/router.py
flask_restful_helper/app_base/file/api_views/api_view.py
flask_restful_helper/app_base/file/logics/logic.py
flask_restful_helper/app_base/file/managers/manager.py
flask_restful_helper/app_base/file/models/model.py
flask_restful_helper/app_base/file/schemas/schema.py
flask_restful_helper/app_base/frontend/__init__.py
flask_restful_helper/app_base/frontend/router.py
flask_restful_helper/app_base/frontend/api_views/api_view.py
flask_restful_helper/app_base/frontend/logics/logic.py
flask_restful_helper/app_base/frontend/managers/manager.py
flask_restful_helper/app_base/frontend/models/model.py
flask_restful_helper/app_base/frontend/schemas/schema.py
flask_restful_helper/app_base/frontend/tests/test.py
flask_restful_helper/app_base/system/__init__.py
flask_restful_helper/app_base/system/router.py
flask_restful_helper/app_base/system/api_views/api_view.py
flask_restful_helper/app_base/system/logics/logic.py
flask_restful_helper/app_base/system/managers/manager.py
flask_restful_helper/app_base/system/models/model.py
flask_restful_helper/app_base/system/schemas/schema.py
flask_restful_helper/app_base/system/tests/test.py
flask_restful_helper/app_base/task/__init__.py
flask_restful_helper/app_base/task/router.py
flask_restful_helper/app_base/task/api_views/api_view.py
flask_restful_helper-1.3.10.dist-info/METADATA
flask_restful_helper-1.3.10.dist-info/WHEEL
flask_restful_helper-1.3.10.dist-info/entry_points.txt
flask_restful_helper-1.3.10.dist-info/top_level.txt
flask_restful_helper-1.3.10.dist-info/RECORD
