Metadata-Version: 2.1
Name: flask-restful-helper
Version: 1.3.10
Summary: A small flask restful framework
Home-page: https://github.com/xianyuntang/flask-restful-helper
Author: Xian-Yun Tang
Author-email: xt1800i@example.com
License: UNKNOWN
Platform: UNKNOWN
Classifier: Programming Language :: Python :: 3
Classifier: License :: OSI Approved :: MIT License
Classifier: Operating System :: OS Independent
Requires-Dist: alembic (==1.6.5)
Requires-Dist: amqp (==5.0.6)
Requires-Dist: aniso8601 (==9.0.1)
Requires-Dist: bcrypt (==3.2.0)
Requires-Dist: billiard (==3.6.4.0)
Requires-Dist: bleach (==3.3.0)
Requires-Dist: cached-property (==1.5.2)
Requires-Dist: celery (==5.1.2)
Requires-Dist: certifi (==2021.5.30)
Requires-Dist: cffi (==1.14.6)
Requires-Dist: chardet (==4.0.0)
Requires-Dist: click (==7.1.2)
Requires-Dist: click-didyoumean (==0.0.3)
Requires-Dist: click-plugins (==1.1.1)
Requires-Dist: click-repl (==0.2.0)
Requires-Dist: colorama (==0.4.4)
Requires-Dist: docutils (==0.17.1)
Requires-Dist: Flask (==2.0.1)
Requires-Dist: Flask-Bcrypt (==0.7.1)
Requires-Dist: Flask-Cors (==3.0.10)
Requires-Dist: Flask-JWT-Extended (==4.2.3)
Requires-Dist: flask-marshmallow (==0.14.0)
Requires-Dist: Flask-Migrate (==3.0.1)
Requires-Dist: Flask-RESTful (==0.3.9)
Requires-Dist: Flask-SQLAlchemy (==2.5.1)
Requires-Dist: Flask-Testing (==0.8.1)
Requires-Dist: greenlet (==1.1.0)
Requires-Dist: idna (==2.10)
Requires-Dist: importlib-metadata (==4.4.0)
Requires-Dist: itsdangerous (==2.0.1)
Requires-Dist: Jinja2 (==3.0.1)
Requires-Dist: keyring (==23.0.1)
Requires-Dist: kombu (==5.1.0)
Requires-Dist: Mako (==1.1.4)
Requires-Dist: MarkupSafe (==2.0.1)
Requires-Dist: marshmallow (==3.12.1)
Requires-Dist: marshmallow-sqlalchemy (==0.26.1)
Requires-Dist: numpy (==1.21.1)
Requires-Dist: packaging (==20.9)
Requires-Dist: pandas (==1.3.1)
Requires-Dist: pkginfo (==1.7.0)
Requires-Dist: prompt-toolkit (==3.0.19)
Requires-Dist: pycparser (==2.20)
Requires-Dist: Pygments (==2.9.0)
Requires-Dist: PyJWT (==2.1.0)
Requires-Dist: PyMySQL (==1.0.2)
Requires-Dist: pyparsing (==2.4.7)
Requires-Dist: python-dateutil (==2.8.2)
Requires-Dist: python-dotenv (==0.18.0)
Requires-Dist: python-editor (==1.0.4)
Requires-Dist: pytz (==2021.1)
Requires-Dist: pywin32-ctypes (==0.2.0)
Requires-Dist: PyYAML (==5.4.1)
Requires-Dist: readme-renderer (==29.0)
Requires-Dist: requests (==2.25.1)
Requires-Dist: requests-toolbelt (==0.9.1)
Requires-Dist: rfc3986 (==1.5.0)
Requires-Dist: six (==1.16.0)
Requires-Dist: SQLAlchemy (==1.4.17)
Requires-Dist: tqdm (==4.61.0)
Requires-Dist: twine (==3.4.1)
Requires-Dist: typing-extensions (==3.10.0.0)
Requires-Dist: urllib3 (==1.26.5)
Requires-Dist: vine (==5.0.0)
Requires-Dist: wcwidth (==0.2.5)
Requires-Dist: webencodings (==0.5.1)
Requires-Dist: Werkzeug (==2.0.1)
Requires-Dist: zipp (==3.4.1)
